<configs>
	<conditional>
		<if cond="mod_loaded('EFT8_DVS_Configs')">
            <append xpath="/traders/trader_item_groups/trader_item_group[@name='groupRangedAllEft']">
                <item name="gunHandgunT3DualAF2011A1S" quality="1,5"/>
                <item name="gunHandgunT3AF2011A1S" quality="1,5"/>
            </append>
        </if>
		<else>
            <append xpath="/traders/trader_item_groups/trader_item_group[@name='groupRangedAll']">
                <item name="gunHandgunT3DualAF2011A1S" quality="1,5"/>
                <item name="gunHandgunT3AF2011A1S" quality="1,5"/>
            </append>
        </else>
    </conditional>
</configs>